z3c.macro-3.0-py3.11-nspkg.pth
z3c/macro/README.rst
z3c/macro/__init__.py
z3c/macro/configure.zcml
z3c/macro/interfaces.py
z3c/macro/meta.zcml
z3c/macro/tales.py
z3c/macro/tests.py
z3c/macro/zcml.py
z3c/macro/zcml.rst
z3c.macro-3.0.dist-info/LICENSE.txt
z3c.macro-3.0.dist-info/METADATA
z3c.macro-3.0.dist-info/WHEEL
z3c.macro-3.0.dist-info/namespace_packages.txt
z3c.macro-3.0.dist-info/top_level.txt
z3c.macro-3.0.dist-info/RECORD
