Metadata-Version: 2.1
Name: z3c.macro
Version: 3.0
Summary: Simpler definition of ZPT macros.
Home-page: https://github.com/zopefoundation/z3c.macro
Author: Roger Ineichen and the Zope Community
Author-email: zope-dev@zope.org
License: ZPL 2.1
Keywords: zope3 macro pagetemplate zpt
Classifier: Development Status :: 5 - Production/Stable
Classifier: Environment :: Web Environment
Classifier: Intended Audience :: Developers
Classifier: License :: OSI Approved :: Zope Public License
Classifier: Programming Language :: Python
Classifier: Programming Language :: Python :: 3
Classifier: Programming Language :: Python :: 3.7
Classifier: Programming Language :: Python :: 3.8
Classifier: Programming Language :: Python :: 3.9
Classifier: Programming Language :: Python :: 3.10
Classifier: Programming Language :: Python :: 3.11
Classifier: Programming Language :: Python :: 3.12
Classifier: Programming Language :: Python :: Implementation :: CPython
Classifier: Programming Language :: Python :: Implementation :: PyPy
Classifier: Natural Language :: English
Classifier: Operating System :: OS Independent
Classifier: Topic :: Internet :: WWW/HTTP
Classifier: Framework :: Zope :: 3
Requires-Python: >=3.7
License-File: LICENSE.txt
Requires-Dist: setuptools
Requires-Dist: zope.component
Requires-Dist: zope.configuration
Requires-Dist: zope.interface
Requires-Dist: zope.pagetemplate >=3.6.2
Requires-Dist: zope.publisher
Requires-Dist: zope.schema
Requires-Dist: zope.tales
Provides-Extra: chameleon
Requires-Dist: z3c.pt >=2.1 ; extra == 'chameleon'
Requires-Dist: z3c.ptcompat >=1.0 ; extra == 'chameleon'
Provides-Extra: test
Requires-Dist: z3c.pt >=2.1 ; extra == 'test'
Requires-Dist: z3c.ptcompat >=1.0 ; extra == 'test'
Requires-Dist: z3c.template ; extra == 'test'
Requires-Dist: zope.browserpage >=3.12 ; extra == 'test'
Requires-Dist: zope.testing ; extra == 'test'
Requires-Dist: zope.testrunner ; extra == 'test'
